bdating_common/__init__.py
bdating_common/api_common.py
bdating_common/auth0_management_helper.py
bdating_common/auth0_token_helper.py
bdating_common/aws_secrets_helper.py
bdating_common/collect_default.py
bdating_common/crypto_helper.py
bdating_common/db_connector.py
bdating_common/enum_translation.yml
bdating_common/errors.py
bdating_common/es_helper.py
bdating_common/event_helper.py
bdating_common/global-bundle.cer
bdating_common/in_app_notif_helper.py
bdating_common/json_logger.py
bdating_common/model.py
bdating_common/model_en.py
bdating_common/model_zh.py
bdating_common/multi_threading.py
bdating_common/notify_helper.py
bdating_common/report_events.py
bdating_common/report_metrics.py
bdating_common/schedule_helper.py
bdating_common/secrets.py
bdating_common/stripe_helper.py
bdating_common/test.py
bdating_common/time_helper.py
bdating_common/utils.py
bdating_common/wallet_helper.py
bdating_common/xero_config.yml
bdating_common/xero_helper.py
bdating_common/xero_utils.py
bdating_common/templates/__init__.py
bdating_common/templates/email/__init__.py
bdating_common/templates/email/customer/__init__.py
bdating_common/templates/email/customer/booking_confirmed.py
bdating_common/templates/email/customer/booking_received.py
bdating_common/templates/email/customer/signup_welcome.py
bdating_python_common-0.9.79.dist-info/METADATA
bdating_python_common-0.9.79.dist-info/WHEEL
bdating_python_common-0.9.79.dist-info/entry_points.txt
bdating_python_common-0.9.79.dist-info/top_level.txt
bdating_python_common-0.9.79.dist-info/RECORD
