Metadata-Version: 2.1
Name: bdating-python-common
Version: 0.9.79
Summary: Bdating common libraries standard library
Home-page: https://github.com/bdating-io/bdating-python-common
Author: Bdating
Author-email: steve@bdating.io
Classifier: Intended Audience :: Developers
Classifier: Programming Language :: Python :: 3 :: Only
Classifier: Topic :: Utilities
Classifier: Typing :: Typed
Requires-Python: >=3.6
Requires-Dist: boto3 <2
Requires-Dist: click-log
Requires-Dist: click
Requires-Dist: dnspython ==2.2.0
Requires-Dist: PyMySQL
Requires-Dist: elasticsearch >8
Requires-Dist: fastapi
Requires-Dist: pydantic-settings
Requires-Dist: PyJWT ==2.1.0
Requires-Dist: cryptography ==3.4.7
Requires-Dist: redis <5
Requires-Dist: auth0-python
Requires-Dist: aiohttp
Requires-Dist: pyyaml ==6.0.1
Requires-Dist: requests
Requires-Dist: web3 <6,>5.0
Requires-Dist: wsproto ==1.2.0
Requires-Dist: aioredis <2
Requires-Dist: xero-python ==1.24.0
Requires-Dist: stripe <6,>5
